{"rows":[{"columns":[{"size":"col-sm-2","containers":[]},{"size":"col-sm-8","containers":[{"genType":"container","proprieties":{"title":"Ficha do Funcionário","tag":"form_1","hasTitle":true,"collapsible":false,"type":"form","collapsed":false},"fields":[{"properties":{"_id":"text_85c9_39c1","label":"Nome","tag":"nome","name":"p_nome","type":"text","maxlength":250,"required":true,"change":false,"readonly":false,"disabled":false,"disablehtml":true,"placeholder":"","desclabel":false,"inputmask":"","size":"12","right":false,"tooltip":false,"disable_copy_paste":false},"style":{"id":"","class":"","inline":""},"options":{"autoTag":true,"rules":[]},"xsl":{"useDefault":true,"template":false},"validation":[{"annotation":"@NotNull","value":"","integer":"","numeric":"","min":"","max":"","message":""}]},{"properties":{"_id":"text_b1fe_db27","label":"Apelido","tag":"apelido","name":"p_apelido","type":"text","maxlength":250,"required":true,"change":false,"readonly":false,"disabled":false,"disablehtml":true,"placeholder":"","desclabel":false,"inputmask":"","size":"12","right":false,"tooltip":false,"disable_copy_paste":false},"style":{"id":"","class":"","inline":""},"options":{"autoTag":true,"rules":[]},"xsl":{"useDefault":true,"template":false},"validation":[{"annotation":"@NotNull","value":"","integer":"","numeric":"","min":"","max":"","message":""}]},{"properties":{"_id":"email_adb2_857a","label":"Email","tag":"email","name":"p_email","type":"email","maxlength":250,"required":false,"change":false,"readonly":false,"disabled":false,"placeholder":"","desclabel":false,"size":"12","right":false,"tooltip":false,"disable_copy_paste":false},"style":{"id":"","class":"","inline":""},"options":{"autoTag":true,"rules":[]},"xsl":{"useDefault":true,"template":null},"validation":[]},{"properties":{"_id":"number_ef18_d75a","label":"Salario","tag":"salario","name":"p_salario","type":"number","min":"","max":"","calculation":false,"mathcal":"","numberformat":"","maxlength":250,"required":true,"change":false,"readonly":false,"disabled":false,"placeholder":"","desclabel":false,"size":"6","right":false,"java-type":"BigDecimal","tooltip":false,"disable_copy_paste":false},"style":{"id":"","class":"","inline":""},"options":{"autoTag":true,"rules":[]},"xsl":{"useDefault":true,"template":false},"validation":[{"annotation":"@NotNull","value":"","integer":"","numeric":"","min":"","max":"","message":""}]},{"properties":{"_id":"date_5d18_d3e6","label":"Data Contratação","tag":"data_contratacao","name":"p_data_contratacao","type":"date","range":false,"disableWeekends":false,"disabledBeforetoday":false,"daysoff":false,"maxlength":250,"required":true,"change":false,"readonly":false,"disabled":false,"placeholder":"","desclabel":false,"size":"6","right":false,"tooltip":false,"disable_copy_paste":false,"class":"primary"},"style":{"id":"","class":"","inline":""},"options":{"autoTag":true,"rules":[]},"xsl":{"useDefault":true,"template":false},"validation":[{"annotation":"@NotNull","value":"","integer":"","numeric":"","min":"","max":"","message":""}]},{"properties":{"_id":"text_74a5_b33e","label":"Telefone","tag":"telefone","name":"p_telefone","type":"text","maxlength":250,"required":true,"change":false,"readonly":false,"disabled":false,"disablehtml":true,"placeholder":"","desclabel":false,"inputmask":"","size":"6","right":false,"tooltip":false,"disable_copy_paste":false},"style":{"id":"","class":"","inline":""},"options":{"autoTag":true,"rules":[]},"xsl":{"useDefault":true,"template":false},"validation":[{"annotation":"@NotNull","value":"","integer":"","numeric":"","min":"","max":"","message":""}]},{"properties":{"_id":"select_feef_4c69","label":"Função","tag":"funcao","name":"p_funcao","type":"select","multiple":false,"tags":false,"load_service_data":false,"domain_value":[],"domain":"","maxlength":250,"required":true,"change":false,"disabled":false,"size":"6","right":false,"java-type":"","tooltip":false,"disable_copy_paste":false},"style":{"id":"","class":"","inline":""},"options":{"autoTag":true,"rules":[]},"xsl":{"useDefault":true,"template":false},"validation":[{"annotation":"@NotNull","value":"","integer":"","numeric":"","min":"","max":"","message":""}]},{"properties":{"_id":"select_5279_c1bc","label":"Departamento","tag":"departamento","name":"p_departamento","type":"select","multiple":false,"tags":false,"load_service_data":false,"domain_value":[],"domain":"","maxlength":250,"required":true,"change":false,"disabled":false,"size":"6","right":false,"java-type":"","tooltip":false,"disable_copy_paste":false},"style":{"id":"","class":"","inline":""},"options":{"autoTag":true,"rules":[]},"xsl":{"useDefault":true,"template":false},"validation":[{"annotation":"@NotNull","value":"","integer":"","numeric":"","min":"","max":"","message":""}]},{"properties":{"_id":"select_3a6b_1595","label":"Coordenador","tag":"coordenador","name":"p_coordenador","type":"select","multiple":false,"tags":false,"load_service_data":false,"domain_value":[],"domain":"","maxlength":250,"required":false,"change":false,"disabled":false,"size":"6","right":false,"java-type":"","tooltip":false,"disable_copy_paste":false},"style":{"id":"","class":"","inline":""},"options":{"autoTag":true,"rules":[]},"xsl":{"useDefault":true,"template":false},"validation":[]},{"properties":{"_id":"link_27a7_704e","label":"Emitir Declaração de Vencimento","tag":"emitir_declaracao_de_vencimento","name":"p_emitir_declaracao_de_vencimento","type":"link","target":"_blank","request_fields":[],"target_fields":"","closerefresh":false,"refresh_components":[],"refresh_submit":false,"adbcli":"","action":"Lista_de_empregados","custom_action":"","action_type":false,"class":"primary","btnSize":"","iconColor":"#333","iconClass":"","img":"fa-file-text-o","maxlength":250,"placeholder":"","desclabel":false,"size":"6","right":false,"tooltip":false,"disable_copy_paste":false},"style":{"id":"","class":"","inline":""},"options":{"autoTag":true,"rules":[]},"xsl":{"useDefault":true,"template":false},"validation":[]},{"properties":{"_id":"file_c663_37c1","label":"Fotografia","tag":"fotografia","name":"p_fotografia","type":"file","accept":["image/*"],"targetrend":"","multiple":false,"rendvalue":false,"maxlength":2000,"required":false,"disabled":false,"size":"6","right":false,"tooltip":false,"disable_copy_paste":false,"class":"primary"},"style":{"id":"","class":"","inline":""},"options":{"autoTag":true,"rules":[]},"xsl":{"useDefault":true,"template":false},"validation":[]},{"properties":{"_id":"hidden_7dee_d777","tag":"id","name":"p_id","type":"hidden","maxlength":250,"java-type":"","tooltip":false,"disable_copy_paste":false},"style":{"id":"","class":"","inline":""},"options":{"autoTag":false,"rules":[]},"xsl":{"useDefault":true,"template":false},"validation":[]}],"style":{"id":"","class":"","inline":""},"options":{"autoTag":false},"id":"form1663419074354","xsl":{"useDefault":true}},{"genType":"container","proprieties":{"tag":"toolsbar_1","type":"toolsbar","align":"centralized","btnSize":"","style":"boxed","vertical":true,"dynamic":false,"outline":false},"fields":[{"properties":{"_id":"button_8f23_205d","label":"Gravar","tag":"gravar","name":"p_gravar","type":"button","target":"submit","request_fields":[],"target_fields":"","closerefresh":false,"refresh_components":[],"refresh_submit":false,"adbcli":"","action":"Funcionario","service":{"code":"","desc":"","proc":"","connectionsReq":[],"fieldsReq":[],"connectionsRes":[],"fieldsRes":[]},"transaction":false,"custom_return":false,"notvalidatefields":false,"class":"primary","iconColor":"#333","iconClass":"","img":"fa-save"},"style":{"id":"","class":"","inline":""},"options":{"autoTag":true,"rules":[]},"xsl":{"useDefault":true,"template":false},"validation":[{"annotation":"@NotNull","value":"","integer":"","numeric":"","min":"","max":"","message":""}]}],"style":{"id":"","class":"","inline":""},"options":{"autoTag":false},"id":"toolsbar1663419520279","xsl":{"useDefault":true}}]},{"size":"col-sm-2","containers":[]}],"propreties":{"class":""}}],"plsql":{"instance":"","table":"","package":"nosi.webapps.gestao_de_recursos_humanos.pages","html":"Funcionario","gentype":"java","replace":false,"label":false,"biztalk":false,"process":false,"subversionpath":""},"css":"","js":"","files":{"css":[],"js":[],"xsl":[]},"blocklyData":"<xml><block type=\"controller\" id=\"0Atu#4UPW]j4uXIqfZzL\" x=\"287\" y=\"38\"></block></xml>"}
